functionwordsets/__init__.py
functionwordsets/_cli.py
functionwordsets/_loader.py
functionwordsets/datasets/__init__.py
functionwordsets/datasets/en_21c.py
functionwordsets/datasets/fr_21c.py
functionwordsets/datasets/gr_5cbc.py
functionwordsets/datasets/it_21c.py
functionwordsets/datasets/la_1cbc.py
functionwordsets/datasets/nl_21c.py
functionwordsets/datasets/oc_13c.py
functionwordsets/datasets/sp_21c.py
functionwordsets-1.2.1.dist-info/licenses/LICENSE
functionwordsets-1.2.1.dist-info/METADATA
functionwordsets-1.2.1.dist-info/WHEEL
functionwordsets-1.2.1.dist-info/entry_points.txt
functionwordsets-1.2.1.dist-info/top_level.txt
functionwordsets-1.2.1.dist-info/RECORD
