Metadata-Version: 2.4
Name: functionwordsets
Version: 1.2.1
Summary: Multilingual and diachronic function-word datasets, with modular composition
Author-email: Florian Cafiero <florian.cafiero@chartes.psl.eu>
License: GPLv3
Project-URL: Homepage, https://github.com/floriancafiero/functionwordsets
Project-URL: Issues, https://github.com/floriancafiero/functionwordsets/issues
Classifier: Programming Language :: Python :: 3
Classifier: License :: OSI Approved :: GNU General Public License v3 (GPLv3)
Classifier: Natural Language :: French
Classifier: Natural Language :: English
Classifier: Natural Language :: Italian
Classifier: Natural Language :: Spanish
Classifier: Natural Language :: Dutch
Classifier: Natural Language :: Latin
Classifier: Natural Language :: Greek
Classifier: Topic :: Text Processing
Requires-Python: >=3.8
License-File: LICENSE
Dynamic: license-file
